aiida_spirit/__init__.py
aiida_spirit/calculations.py
aiida_spirit/cli.py
aiida_spirit/helpers.py
aiida_spirit/parsers.py
aiida_spirit-0.1.0a0.dist-info/LICENSE
aiida_spirit-0.1.0a0.dist-info/METADATA
aiida_spirit-0.1.0a0.dist-info/WHEEL
aiida_spirit-0.1.0a0.dist-info/entry_points.txt
aiida_spirit-0.1.0a0.dist-info/top_level.txt
aiida_spirit-0.1.0a0.dist-info/RECORD
