Metadata-Version: 2.1
Name: aiida-spirit
Version: 0.1.0a0
Summary: AiiDA plugin for the spirit code
Home-page: https://github.com/JuDFTteam/aiida-spirit
Author: The JuDFT Team
Author-email: p.ruessmann@fz-juelich.de
License: MIT
Platform: UNKNOWN
Classifier: Programming Language :: Python
Classifier: Intended Audience :: Science/Research
Classifier: License :: OSI Approved :: MIT License
Classifier: Natural Language :: English
Classifier: Framework :: AiiDA
Requires-Dist: aiida-core (<2.0.0,>=1.1.0)
Requires-Dist: sqlalchemy (<1.4)
Requires-Dist: numpy
Provides-Extra: docs
Requires-Dist: sphinx ; extra == 'docs'
Requires-Dist: sphinxcontrib-contentui ; extra == 'docs'
Requires-Dist: sphinx-rtd-theme ; extra == 'docs'
Requires-Dist: sphinxcontrib-details-directive ; (python_version >= "3.0") and extra == 'docs'
Provides-Extra: pre-commit
Requires-Dist: astroid (<2.5) ; extra == 'pre-commit'
Requires-Dist: pre-commit (~=2.2) ; extra == 'pre-commit'
Requires-Dist: pylint (~=2.5.0) ; extra == 'pre-commit'
Provides-Extra: testing
Requires-Dist: pgtest (~=1.3.1) ; extra == 'testing'
Requires-Dist: wheel (~=0.31) ; extra == 'testing'
Requires-Dist: coverage ; extra == 'testing'
Requires-Dist: pytest (<5.0.0,~=3.6) ; extra == 'testing'
Requires-Dist: pytest-cov ; extra == 'testing'
